social_ethosa/ConfigReader.py
social_ethosa/UtilsManager.py
social_ethosa/__init__.py
social_ethosa/utils.py
social_ethosa/botwrapper/BetterBotBase.py
social_ethosa/botwrapper/BetterBotWrapper.py
social_ethosa/botwrapper/BetterUser.py
social_ethosa/botwrapper/BotBase.py
social_ethosa/botwrapper/BotWrapper.py
social_ethosa/botwrapper/User.py
social_ethosa/botwrapper/__init__.py
social_ethosa/eMath/Matrix.py
social_ethosa/eMath/Path.py
social_ethosa/eMath/Point.py
social_ethosa/eMath/Point2D.py
social_ethosa/eMath/Rectangle.py
social_ethosa/eMath/Sequences.py
social_ethosa/eMath/Vector2.py
social_ethosa/eMath/__init__.py
social_ethosa/extra/Regexp.py
social_ethosa/extra/__init__.py
social_ethosa/extra/eList.py
social_ethosa/extra/eQueue.py
social_ethosa/extra/logManager.py
social_ethosa/extra/markovChains.py
social_ethosa/extra/algorithms/__init__.py
social_ethosa/extra/algorithms/markov.py
social_ethosa/graphics/EColor.py
social_ethosa/graphics/EImage.py
social_ethosa/graphics/__init__.py
social_ethosa/net/__init__.py
social_ethosa/net/blogger.py
social_ethosa/net/hentasis.py
social_ethosa/net/jdoodlecom.py
social_ethosa/net/pastebin.py
social_ethosa/net/pr0n.py
social_ethosa/net/tpdne.py
social_ethosa/net/tracemoe.py
social_ethosa/net/uploader.py
social_ethosa/net/vkaudio.py
social_ethosa/net/vkauth.py
social_ethosa/net/vkcom.py
social_ethosa/net/yandex.py
social_ethosa/net/yummyanime.py
social_ethosa-0.6.4.dist-info/LICENSE
social_ethosa-0.6.4.dist-info/METADATA
social_ethosa-0.6.4.dist-info/WHEEL
social_ethosa-0.6.4.dist-info/top_level.txt
social_ethosa-0.6.4.dist-info/RECORD
