Metadata-Version: 2.1
Name: social-ethosa
Version: 0.6.4
Summary: The social ethosa library for Python
Home-page: https://github.com/Ethosa/social_ethosa
Author: Ethosa
Author-email: social.ethosa@gmail.com
License: LGPLv3
Project-URL: Github, https://github.com/Ethosa/social_ethosa
Project-URL: Documentation, https://github.com/Ethosa/social_ethosa/blob/master/README.md
Keywords: vk api botwrapper network math social ethosa
Platform: UNKNOWN
Classifier: Development Status :: 4 - Beta
Classifier: Programming Language :: Python :: 3
Classifier: Programming Language :: Python :: 3.4
Classifier: Programming Language :: Python :: 3.5
Classifier: Programming Language :: Python :: 3.6
Classifier: Programming Language :: Python :: 3.7
Classifier: License :: OSI Approved :: GNU Lesser General Public License v3 (LGPLv3)
Classifier: Operating System :: OS Independent
Requires-Python: >=3
Requires-Dist: requests
Requires-Dist: regex
